{
  "VISA": [
    {
      "src": "/img/visa-card-5.png",
      "alt": "Raw Stone熾熱赤焰"
    },
    {
      "src": "/img/visa-card-6.png",
      "alt": "Raw Stone金色陽光"
    },
    {
      "src": "/img/visa-card-2.png",
      "alt": "Raw Stone翠綠春意"
    },
    {
      "src": "/img/visa-card-1.png",
      "alt": "Raw Stone晴空淺藍"
    },
    {
      "src": "/img/visa-card-3.png",
      "alt": "Raw Stone深海浪潮"
    },
    {
      "src": "/img/visa-card-4.png",
      "alt": "Raw Stone紫禁神秘"
    }
  ],
  "MasterCard": [
    {
      "src": "/img/card_alex.png",
      "alt": "卡片7"
    },
    {
      "src": "/img/card_alex.png",
      "alt": "卡片8"
    },
    {
      "src": "/img/card_alex.png",
      "alt": "卡片9"
    }
  ],
  "JCB": [
    {
      "src": "/img/card4.png",
      "alt": "卡片4"
    },
    {
      "src": "/img/card5.png",
      "alt": "卡片5"
    },
    {
      "src": "/img/card6.png",
      "alt": "卡片6"
    }
  ]
}
